{
  "main": {
    "id": "9465b431d278ed03",
    "type": "split",
    "children": [
      {
        "id": "9868e04a3ab1b6b6",
        "type": "tabs",
        "children": [
          {
            "id": "358139341c13846c",
            "type": "leaf",
            "pinned": true,
            "state": {
              "type": "canvas",
              "state": {
                "file": "Artist-Map.canvas",
                "viewState": {
                  "x": -155,
                  "y": -55,
                  "zoom": -0.8284620342891427
                }
              },
              "pinned": true
            }
          },
          {
            "id": "93903e8f49dd9ead",
            "type": "leaf",
            "state": {
              "type": "markdown",
              "state": {
                "file": "Diary/Dairy Index.md",
                "mode": "source",
                "source": false
              }
            }
          },
          {
            "id": "8a513f31d7ec76ec",
            "type": "leaf",
            "pinned": true,
            "state": {
              "type": "graph",
              "state": {},
              "pinned": true
            }
          },
          {
            "id": "ba798761235384c5",
            "type": "leaf",
            "state": {
              "type": "markdown",
              "state": {
                "file": "reference-name/Artists&Scholars.md",
                "mode": "source",
                "source": false
              }
            }
          },
          {
            "id": "21603736f7adeb1c",
            "type": "leaf",
            "state": {
              "type": "markdown",
              "state": {
                "file": "Diary/2024-01-12.md",
                "mode": "source",
                "source": false
              }
            }
          },
          {
            "id": "444159dc1efcf33f",
            "type": "leaf",
            "state": {
              "type": "markdown",
              "state": {
                "file": "Diary/2024-01-12.md",
                "mode": "source",
                "source": false
              }
            }
          },
          {
            "id": "dc81fe00ba4672eb",
            "type": "leaf",
            "state": {
              "type": "markdown",
              "state": {
                "file": "hello.md",
                "mode": "source",
                "source": false
              }
            }
          },
          {
            "id": "9d01e82f5f8dd6f2",
            "type": "leaf",
            "state": {
              "type": "markdown",
              "state": {
                "file": "Diary/🥗.md",
                "mode": "source",
                "source": false
              }
            }
          }
        ],
        "currentTab": 7
      }
    ],
    "direction": "vertical"
  },
  "left": {
    "id": "dd556a47409e91a9",
    "type": "split",
    "children": [
      {
        "id": "5038383a015d14a2",
        "type": "tabs",
        "children": [
          {
            "id": "9ed233b0a6d5f138",
            "type": "leaf",
            "state": {
              "type": "file-explorer",
              "state": {
                "sortOrder": "alphabetical"
              }
            }
          },
          {
            "id": "3b0228c42ea3a3c5",
            "type": "leaf",
            "state": {
              "type": "search",
              "state": {
                "query": "",
                "matchingCase": false,
                "explainSearch": false,
                "collapseAll": false,
                "extraContext": false,
                "sortOrder": "alphabetical"
              }
            }
          },
          {
            "id": "d581bc466164a753",
            "type": "leaf",
            "state": {
              "type": "bookmarks",
              "state": {}
            }
          }
        ]
      }
    ],
    "direction": "horizontal",
    "width": 300
  },
  "right": {
    "id": "4df0a60cafcfd115",
    "type": "split",
    "children": [
      {
        "id": "e6b89bb79d12b25f",
        "type": "tabs",
        "children": [
          {
            "id": "969b9b6b10f3e4e7",
            "type": "leaf",
            "state": {
              "type": "backlink",
              "state": {
                "file": "Diary/🥗.md",
                "collapseAll": false,
                "extraContext": false,
                "sortOrder": "alphabetical",
                "showSearch": false,
                "searchQuery": "",
                "backlinkCollapsed": false,
                "unlinkedCollapsed": true
              }
            }
          },
          {
            "id": "5e300745c605955c",
            "type": "leaf",
            "state": {
              "type": "outgoing-link",
              "state": {
                "file": "Diary/🥗.md",
                "linksCollapsed": false,
                "unlinkedCollapsed": true
              }
            }
          },
          {
            "id": "fa86848d1d1bd5ad",
            "type": "leaf",
            "state": {
              "type": "tag",
              "state": {
                "sortOrder": "frequency",
                "useHierarchy": true
              }
            }
          },
          {
            "id": "3c31ee299dc5acd7",
            "type": "leaf",
            "state": {
              "type": "outline",
              "state": {
                "file": "Diary/🥗.md"
              }
            }
          }
        ]
      }
    ],
    "direction": "horizontal",
    "width": 300,
    "collapsed": true
  },
  "left-ribbon": {
    "hiddenItems": {
      "switcher:Open quick switcher": false,
      "graph:Open graph view": false,
      "canvas:Create new canvas": false,
      "daily-notes:Open today's daily note": false,
      "templates:Insert template": false,
      "command-palette:Open command palette": false,
      "workspaces:Manage workspace layouts": false,
      "obsidian-daily-notes-viewer:Open Viewer": false,
      "templater-obsidian:Templater": false,
      "digitalgarden:Digital Garden Publication Center": false
    }
  },
  "active": "9d01e82f5f8dd6f2",
  "lastOpenFiles": [
    "Diary/2024-01-12.md",
    "hello.md",
    "My Garden.md",
    "tech-note/Gatsby-blog-Log.md",
    "Diary/All-Dairies.md",
    "Diary/Dairy Index.md",
    "test.md",
    "No.md",
    "Diary/Dairy Template.md",
    "Diary/2024-01-10.md",
    "Diary/2024-01-09.md",
    "artists/sculpture/Hannah-Levy.md",
    "artists/music/Alice Coltrane.md",
    "Diary/2024-01-11.md",
    "note-templates/New Note Template.md",
    "Untitled 1.md",
    "note-templates",
    "reference-name/Artists&Scholars.md",
    "random-thoughts/about-writing-in-Chinese.md",
    "Artist-Map.canvas",
    "random-thoughts/Talking.md",
    "tech-note/React.md",
    "2024-01-11.md",
    "watch-list/Animation/Chilly-and-Milly.md",
    "watch-list/Animation",
    "watch-list/Animation.md",
    "Diary/Diary-list",
    "tech-note",
    "reading-notes/Transhumanism.md",
    "reading-notes",
    "random-thoughts",
    "reference-name/wanting-to-watch.md",
    "Untitled.canvas",
    "artist-map.canvas",
    "Artist Map.canvas"
  ]
}